bw_plex/__init__.py
bw_plex/__main__.py
bw_plex/audio.py
bw_plex/chromecast.py
bw_plex/cli.py
bw_plex/config.py
bw_plex/credits.py
bw_plex/db.py
bw_plex/edl.py
bw_plex/hashing.py
bw_plex/misc.py
bw_plex/plex.py
bw_plex/tools.py
bw_plex/video.py
bw_plex/audfprint/.gitignore
bw_plex/audfprint/LICENSE
bw_plex/audfprint/Makefile
bw_plex/audfprint/README-dpwe-audfprint.txt
bw_plex/audfprint/README.md
bw_plex/audfprint/__init__.py
bw_plex/audfprint/audfprint.py
bw_plex/audfprint/audfprint_analyze.py
bw_plex/audfprint/audfprint_match.py
bw_plex/audfprint/audio_read.py
bw_plex/audfprint/comp_file_lines.py
bw_plex/audfprint/config.txt
bw_plex/audfprint/config_tiny.txt
bw_plex/audfprint/dpwe_builder.py
bw_plex/audfprint/dpwe_matcher.py
bw_plex/audfprint/hash_table.py
bw_plex/audfprint/requirements.txt
bw_plex/audfprint/searching_for_ads.md
bw_plex-0.0.9.dist-info/METADATA
bw_plex-0.0.9.dist-info/WHEEL
bw_plex-0.0.9.dist-info/entry_points.txt
bw_plex-0.0.9.dist-info/top_level.txt
bw_plex-0.0.9.dist-info/RECORD
