Metadata-Version: 2.1
Name: bw-plex
Version: 0.0.9
Summary: Skip intros.
Home-page: https://github.com/Hellowlol/bw_plex
Author: hellowlol
Author-email: hellowlol1@gmail.com
License: GPL3
Requires-Dist: librosa
Requires-Dist: plexapi (>=3.0.6)
Requires-Dist: joblib
Requires-Dist: numpy
Requires-Dist: docopt
Requires-Dist: click
Requires-Dist: scipy
Requires-Dist: matplotlib
Requires-Dist: psutil
Requires-Dist: srt
Requires-Dist: sqlalchemy
Requires-Dist: configobj
Requires-Dist: youtube-dl
Requires-Dist: beautifulsoup4
Requires-Dist: html5lib
Requires-Dist: tablib
Requires-Dist: lomond (>=0.3.3)
Requires-Dist: PyChromecast (>=3.2.2)
Requires-Dist: pysubs2 (>=0.2.4)
Provides-Extra: all
Requires-Dist: pytesseract ; extra == 'all'
Requires-Dist: opencv-contrib-python ; extra == 'all'
Requires-Dist: pocketsphinx ; extra == 'all'
Requires-Dist: SpeechRecognition ; extra == 'all'
Provides-Extra: audio
Requires-Dist: pocketsphinx ; extra == 'audio'
Requires-Dist: SpeechRecognition ; extra == 'audio'
Provides-Extra: video
Requires-Dist: pytesseract ; extra == 'video'
Requires-Dist: opencv-contrib-python ; extra == 'video'
